{
  "GET_META_INFO": {
    "RESULT": {
      "STATUS": 0,
      "ERROR_MSG": "正常に終了しました。",
      "DATE": "2026-02-19T19:31:58.029+09:00"
    },
    "PARAMETER": {
      "LANG": "J",
      "STATS_DATA_ID": "0000010110",
      "DATA_FORMAT": "J"
    },
    "METADATA_INF": {
      "TABLE_INF": {
        "@id": "0000010110",
        "STAT_NAME": {
          "@code": "00200502",
          "$": "社会・人口統計体系"
        },
        "GOV_ORG": {
          "@code": "00200",
          "$": "総務省"
        },
        "STATISTICS_NAME": "都道府県データ 基礎データ",
        "TITLE": {
          "@no": "0000010110",
          "$": "Ｊ　福祉・社会保障"
        },
        "CYCLE": "年度次",
        "SURVEY_DATE": 0,
        "OPEN_DATE": "2025-02-21",
        "SMALL_AREA": 0,
        "COLLECT_AREA": "全国",
        "MAIN_CATEGORY": {
          "@code": "99",
          "$": "その他"
        },
        "SUB_CATEGORY": {
          "@code": "99",
          "$": "その他"
        },
        "OVERALL_TOTAL_NUMBER": 445008,
        "UPDATED_DATE": "2026-02-17",
        "STATISTICS_NAME_SPEC": {
          "TABULATION_CATEGORY": "都道府県データ",
          "TABULATION_SUB_CATEGORY1": "基礎データ"
        },
        "DESCRIPTION": {
          "TABULATION_CATEGORY_EXPLANATION": "社会・人口統計体系の都道府県ごとに集計したデータを提供します。"
        },
        "TITLE_SPEC": {
          "TABLE_NAME": "Ｊ　福祉・社会保障"
        }
      },
      "CLASS_INF": {
        "CLASS_OBJ": [
          {
            "@id": "tab",
            "@name": "観測値",
            "CLASS": {
              "@code": "00001",
              "@name": "観測値",
              "@level": "1"
            }
          },
          {
            "@id": "cat01",
            "@name": "Ｊ　福祉・社会保障",
            "EXPLANATION": [
              {
                "@id": "J2503",
                "$": "幼保連携型認定こども園，保育所型認定こども園及び保育所を含む。"
              },
              {
                "@id": "J250301",
                "$": "幼保連携型認定こども園，保育所型認定こども園及び保育所を含む。"
              },
              {
                "@id": "J2505",
                "$": "幼保連携型認定こども園，保育所型認定こども園及び保育所を含む。"
              },
              {
                "@id": "J250501",
                "$": "幼保連携型認定こども園，保育所型認定こども園及び保育所を含む。"
              },
              {
                "@id": "J2506",
                "$": "幼保連携型認定こども園，保育所型認定こども園及び保育所を含む。"
              },
              {
                "@id": "J250604",
                "$": "幼保連携型認定こども園，保育所型認定こども園及び保育所を含む。"
              },
              {
                "@id": "J2508",
                "$": "幼保連携型認定こども園，保育所型認定こども園及び保育所を含む。"
              }
            ],
            "CLASS": [
              {
                "@code": "J1101",
                "@name": "J1101_生活保護被保護実世帯数",
                "@level": "1",
                "@unit": "世帯"
              },
              {
                "@code": "J1102",
                "@name": "J1102_現に保護を受けた生活保護被保護実世帯数",
                "@level": "1",
                "@unit": "世帯"
              },
              {
                "@code": "J110201",
                "@name": "J110201_現に保護を受けた生活保護被保護実世帯数（母子世帯）",
                "@level": "1",
                "@unit": "世帯"
              },
              {
                "@code": "J110202",
                "@name": "J110202_現に保護を受けた生活保護被保護実世帯数（傷病・障害者世帯）",
                "@level": "1",
                "@unit": "世帯"
              },
              {
                "@code": "J110203",
                "@name": "J110203_現に保護を受けた生活保護被保護実世帯数（高齢者世帯）",
                "@level": "1",
                "@unit": "世帯"
              },
              {
                "@code": "J110204",
                "@name": "J110204_現に保護を受けた医療扶助単給世帯数",
                "@level": "1",
                "@unit": "世帯"
              },
              {
                "@code": "J1103",
                "@name": "J1103_保護開始世帯数",
                "@level": "1",
                "@unit": "世帯"
              },
              {
                "@code": "J110301",
                "@name": "J110301_保護開始世帯数（母子世帯）",
                "@level": "1",
                "@unit": "世帯"
              },
              {
                "@code": "J110302",
                "@name": "J110302_保護開始世帯数（高齢者世帯）",
                "@level": "1",
                "@unit": "世帯"
              },
              {
                "@code": "J110303",
                "@name": "J110303_保護開始世帯数（その他の世帯）",
                "@level": "1",
                "@unit": "世帯"
              },
              {
                "@code": "J1104",
                "@name": "J1104_生活保護扶助世帯数",
                "@level": "1",
                "@unit": "世帯"
              },
              {
                "@code": "J110401",
                "@name": "J110401_生活保護扶助世帯数（生活）",
                "@level": "1",
                "@unit": "世帯"
              },
              {
                "@code": "J110402",
                "@name": "J110402_生活保護扶助世帯数（住宅）",
                "@level": "1",
                "@unit": "世帯"
              },
              {
                "@code": "J110403",
                "@name": "J110403_生活保護扶助世帯数（教育）",
                "@level": "1",
                "@unit": "世帯"
              },
              {
                "@code": "J110404",
                "@name": "J110404_生活保護扶助世帯数（医療）",
                "@level": "1",
                "@unit": "世帯"
              },
              {
                "@code": "J1104041",
                "@name": "J1104041_生活保護扶助世帯数（介護）",
                "@level": "1",
                "@unit": "世帯"
              },
              {
                "@code": "J110405",
                "@name": "J110405_生活保護扶助世帯数（出産）",
                "@level": "1",
                "@unit": "世帯"
              },
              {
                "@code": "J110406",
                "@name": "J110406_生活保護扶助世帯数（生業）",
                "@level": "1",
                "@unit": "世帯"
              },
              {
                "@code": "J110407",
                "@name": "J110407_生活保護扶助世帯数（葬祭）",
                "@level": "1",
                "@unit": "世帯"
              },
              {
                "@code": "J1105",
                "@name": "J1105_生活保護被保護実人員",
                "@level": "1",
                "@unit": "人"
              },
              {
                "@code": "J1106",
                "@name": "J1106_生活保護扶助人員",
                "@level": "1",
                "@unit": "人"
              },
              {
                "@code": "J110601",
                "@name": "J110601_生活保護扶助人員（生活）",
                "@level": "1",
                "@unit": "人"
              },
              {
                "@code": "J110602",
                "@name": "J110602_生活保護扶助人員（住宅）",
                "@level": "1",
                "@unit": "人"
              },
              {
                "@code": "J110603",
                "@name": "J110603_生活保護扶助人員（教育）",
                "@level": "1",
                "@unit": "人"
              },
              {
                "@code": "J110604",
                "@name": "J110604_生活保護扶助人員（医療）",
                "@level": "1",
                "@unit": "人"
              },
              {
                "@code": "J1106041",
                "@name": "J1106041_生活保護扶助人員（介護）",
                "@level": "1",
                "@unit": "人"
              },
              {
                "@code": "J110605",
                "@name": "J110605_生活保護扶助人員（出産）",
                "@level": "1",
                "@unit": "人"
              },
              {
                "@code": "J110606",
                "@name": "J110606_生活保護扶助人員（生業）",
                "@level": "1",
                "@unit": "人"
              },
              {
                "@code": "J110607",
                "@name": "J110607_生活保護扶助人員（葬祭）",
                "@level": "1",
                "@unit": "人"
              },
              {
                "@code": "J110702",
                "@name": "J110702_生活保護被保護高齢者数（65歳以上）",
                "@level": "1",
                "@unit": "人"
              },
              {
                "@code": "J110703",
                "@name": "J110703_教育扶助受給人員、小－中学校",
                "@level": "1",
                "@unit": "人"
              },
              {
                "@code": "J110704",
                "@name": "J110704_高等学校等就学費受給人員",
                "@level": "1",
                "@unit": "人"
              },
              {
                "@code": "J1200",
                "@name": "J1200_身体障害者手帳交付数",
                "@level": "1",
                "@unit": "人"
              },
              {
                "@code": "J120001",
                "@name": "J120001_身体障害者手帳交付数（18歳以上）",
                "@level": "1",
                "@unit": "人"
              },
              {
                "@code": "J120002",
                "@name": "J120002_身体障害者手帳交付数（18歳未満）",
                "@level": "1",
                "@unit": "人"
              },
              {
                "@code": "J1201",
                "@name": "J1201_身体障害者手帳交付数（視覚障害）",
                "@level": "1",
                "@unit": "人"
              },
              {
                "@code": "J120101",
                "@name": "J120101_身体障害者手帳交付数（視覚障害）（18歳以上）",
                "@level": "1",
                "@unit": "人"
              },
              {
                "@code": "J120102",
                "@name": "J120102_身体障害者手帳交付数（視覚障害）（18歳未満）",
                "@level": "1",
                "@unit": "人"
              },
              {
                "@code": "J1202",
                "@name": "J1202_身体障害者手帳交付数（聴覚・平衡機能障害）",
                "@level": "1",
                "@unit": "人"
              },
              {
                "@code": "J120201",
                "@name": "J120201_身体障害者手帳交付数（聴覚・平衡機能障害）（18歳以上）",
                "@level": "1",
                "@unit": "人"
              },
              {
                "@code": "J120202",
                "@name": "J120202_身体障害者手帳交付数（聴覚・平衡機能障害）（18歳未満）",
                "@level": "1",
                "@unit": "人"
              },
              {
                "@code": "J1203",
                "@name": "J1203_身体障害者手帳交付数（音声・言語・そしゃく機能障害）",
                "@level": "1",
                "@unit": "人"
              },
              {
                "@code": "J120301",
                "@name": "J120301_身体障害者手帳交付数（音声・言語・そしゃく機能障害）（18歳以上）",
                "@level": "1",
                "@unit": "人"
              },
              {
                "@code": "J120302",
                "@name": "J120302_身体障害者手帳交付数（音声・言語・そしゃく機能障害）（18歳未満）",
                "@level": "1",
                "@unit": "人"
              },
              {
                "@code": "J1204",
                "@name": "J1204_身体障害者手帳交付数（肢体不自由障害）",
                "@level": "1",
                "@unit": "人"
              },
              {
                "@code": "J120401",
                "@name": "J120401_身体障害者手帳交付数（肢体不自由障害）（18歳以上）",
                "@level": "1",
                "@unit": "人"
              },
              {
                "@code": "J120402",
                "@name": "J120402_身体障害者手帳交付数（肢体不自由障害）（18歳未満）",
                "@level": "1",
                "@unit": "人"
              },
              {
                "@code": "J1205",
                "@name": "J1205_身体障害者手帳交付数（内部障害）",
                "@level": "1",
                "@unit": "人"
              },
              {
                "@code": "J120501",
                "@name": "J120501_身体障害者手帳交付数（内部障害）（18歳以上）",
                "@level": "1",
                "@unit": "人"
              },
              {
                "@code": "J120502",
                "@name": "J120502_身体障害者手帳交付数（内部障害）（18歳未満）",
                "@level": "1",
                "@unit": "人"
              },
              {
                "@code": "J1210",
                "@name": "J1210_身体障害者補装具交付決定件数",
                "@level": "1",
                "@unit": "件"
              },
              {
                "@code": "J1212",
                "@name": "J1212_身体障害者補装具修理決定件数",
                "@level": "1",
                "@unit": "件"
              },
              {
                "@code": "J1213",
                "@name": "J1213_身体障害者補装具修理負担額",
                "@level": "1",
                "@unit": "円"
              },
              {
                "@code": "J121301",
                "@name": "J121301_身体障害者補装具修理負担額（公費負担額）",
                "@level": "1",
                "@unit": "円"
              },
              {
                "@code": "J1301",
                "@name": "J1301_精神障害者保健福祉手帳交付件数",
                "@level": "1",
                "@unit": "件"
              },
              {
                "@code": "J130101",
                "@name": "J130101_精神障害保健福祉手帳交付件数（1級）",
                "@level": "1",
                "@unit": "件"
              },
              {
                "@code": "J130102",
                "@name": "J130102_精神障害保健福祉手帳交付件数（2級）",
                "@level": "1",
                "@unit": "件"
              },
              {
                "@code": "J130103",
                "@name": "J130103_精神障害保健福祉手帳交付件数（3級）",
                "@level": "1",
                "@unit": "件"
              },
              {
                "@code": "J1401",
                "@name": "J1401_児童扶養手当受給者数",
                "@level": "1",
                "@unit": "人"
              },
              {
                "@code": "J1501",
                "@name": "J1501_知的障害者療育手帳交付数",
                "@level": "1",
                "@unit": "人"
              },
              {
                "@code": "J2101",
                "@name": "J2101_社会福祉施設数",
                "@level": "1",
                "@unit": "所"
              },
              {
                "@code": "J2103",
                "@name": "J2103_社会福祉施設従事者数（常勤）",
                "@level": "1",
                "@unit": "人"
              },
              {
                "@code": "J2201",
                "@name": "J2201_保護施設数（詳細票）（医療保護施設を除く）",
                "@level": "1",
                "@unit": "所"
              },
              {
                "@code": "J2202",
                "@name": "J2202_保護施設定員数（医療保護施設を含む）",
                "@level": "1",
                "@unit": "人"
              },
              {
                "@code": "J2203",
                "@name": "J2203_保護施設定員数（詳細票）（医療保護施設を除く）",
                "@level": "1",
                "@unit": "人"
              },
              {
                "@code": "J2205",
                "@name": "J2205_保護施設在所者数（医療保護施設を含む）",
                "@level": "1",
                "@unit": "人"
              },
              {
                "@code": "J2206",
                "@name": "J2206_保護施設在所者数（詳細票）（医療保護施設を除く）",
                "@level": "1",
                "@unit": "人"
              },
              {
                "@code": "J2209",
                "@name": "J2209_保護施設従事者数（医療保護施設を除く）（専任）",
                "@level": "1",
                "@unit": "人"
              },
              {
                "@code": "J2212",
                "@name": "J2212_保護施設従事者数（詳細票）（医療保護施設を除く）（常勤）",
                "@level": "1",
                "@unit": "人"
              },
              {
                "@code": "J2221",
                "@name": "J2221_保護施設数（基本票）（医療保護施設を除く）",
                "@level": "1",
                "@unit": "所"
              },
              {
                "@code": "J2300",
                "@name": "J2300_老人福祉関係施設数",
                "@level": "1",
                "@unit": "所"
              },
              {
                "@code": "J2301",
                "@name": "J2301_老人福祉施設数（詳細票）",
                "@level": "1",
                "@unit": "所"
              },
              {
                "@code": "J230111",
                "@name": "J230111_養護老人ホーム数（詳細票）",
                "@level": "1",
                "@unit": "所"
              },
              {
                "@code": "J230112",
                "@name": "J230112_養護老人ホーム定員数（詳細票）",
                "@level": "1",
                "@unit": "人"
              },
              {
                "@code": "J230113",
                "@name": "J230113_養護老人ホーム在所者数（詳細票）",
                "@level": "1",
                "@unit": "人"
              },
              {
                "@code": "J230115",
                "@name": "J230115_養護老人ホーム従事者数（詳細票）（常勤）",
                "@level": "1",
                "@unit": "人"
              },
              {
                "@code": "J230121",
                "@name": "J230121_介護老人福祉施設数（詳細票）",
                "@level": "1",
                "@unit": "所"
              },
              {
                "@code": "J230124",
                "@name": "J230124_介護老人福祉施設定員数（詳細票）",
                "@level": "1",
                "@unit": "人"
              },
              {
                "@code": "J230125",
                "@name": "J230125_介護老人福祉施設在所者数（詳細票）",
                "@level": "1",
                "@unit": "人"
              },
              {
                "@code": "J230126",
                "@name": "J230126_介護老人福祉施設従事者数（詳細票）",
                "@level": "1",
                "@unit": "人"
              },
              {
                "@code": "J230127",
                "@name": "J230127_介護老人福祉施設数（基本票）",
                "@level": "1",
                "@unit": "所"
              },
              {
                "@code": "J230128",
                "@name": "J230128_介護老人福祉施設定員数（基本票）",
                "@level": "1",
                "@unit": "人"
              },
              {
                "@code": "J230131",
                "@name": "J230131_軽費老人ホーム数（詳細票）",
                "@level": "1",
                "@unit": "所"
              },
              {
                "@code": "J230132",
                "@name": "J230132_軽費老人ホーム定員数（詳細票）",
                "@level": "1",
                "@unit": "人"
              },
              {
                "@code": "J230133",
                "@name": "J230133_軽費老人ホーム在所者数（詳細票）",
                "@level": "1",
                "@unit": "人"
              },
              {
                "@code": "J230135",
                "@name": "J230135_軽費老人ホーム従事者数（詳細票）（常勤）",
                "@level": "1",
                "@unit": "人"
              },
              {
                "@code": "J230141",
                "@name": "J230141_老人福祉センター数",
                "@level": "1",
                "@unit": "所"
              },
              {
                "@code": "J230144",
                "@name": "J230144_老人福祉センター従事者数（専任）",
                "@level": "1",
                "@unit": "人"
              },
              {
                "@code": "J230145",
                "@name": "J230145_老人福祉センター従事者数（常勤）",
                "@level": "1",
                "@unit": "人"
              },
              {
                "@code": "J230155",
                "@name": "J230155_訪問介護事業所数",
                "@level": "1",
                "@unit": "所"
              },
              {
                "@code": "J230156",
                "@name": "J230156_訪問介護利用者数",
                "@level": "1",
                "@unit": "人"
              },
              {
                "@code": "J230162",
                "@name": "J230162_訪問入浴介護事業所数",
                "@level": "1",
                "@unit": "所"
              },
              {
                "@code": "J230163",
                "@name": "J230163_訪問入浴介護利用者数",
                "@level": "1",
                "@unit": "人"
              },
              {
                "@code": "J230165",
                "@name": "J230165_通所介護事業所数",
                "@level": "1",
                "@unit": "所"
              },
              {
                "@code": "J230166",
                "@name": "J230166_通所介護定員数",
                "@level": "1",
                "@unit": "人"
              },
              {
                "@code": "J230167",
                "@name": "J230167_通所介護従事者数",
                "@level": "1",
                "@unit": "人"
              },
              {
                "@code": "J230168",
                "@name": "J230168_通所介護利用者数",
                "@level": "1",
                "@unit": "人"
              },
              {
                "@code": "J230171",
                "@name": "J230171_短期入所生活介護事業所数",
                "@level": "1",
                "@unit": "所"
              },
              {
                "@code": "J230172",
                "@name": "J230172_短期入所生活介護定員数",
                "@level": "1",
                "@unit": "人"
              },
              {
                "@code": "J230173",
                "@name": "J230173_短期入所生活介護従事者数",
                "@level": "1",
                "@unit": "人"
              },
              {
                "@code": "J230174",
                "@name": "J230174_短期入所生活介護利用者数",
                "@level": "1",
                "@unit": "人"
              },
              {
                "@code": "J230181",
                "@name": "J230181_居宅介護支援事業所数",
                "@level": "1",
                "@unit": "所"
              },
              {
                "@code": "J230182",
                "@name": "J230182_居宅介護支援事業利用者数",
                "@level": "1",
                "@unit": "人"
              },
              {
                "@code": "J230191",
                "@name": "J230191_老人介護支援センター数",
                "@level": "1",
                "@unit": "所"
              },
              {
                "@code": "J2302",
                "@name": "J2302_その他の老人福祉施設数",
                "@level": "1",
                "@unit": "所"
              },
              {
                "@code": "J230211",
                "@name": "J230211_老人憩の家数",
                "@level": "1",
                "@unit": "所"
              },
              {
                "@code": "J230214",
                "@name": "J230214_老人憩の家従事者数（専任）",
                "@level": "1",
                "@unit": "人"
              },
              {
                "@code": "J230215",
                "@name": "J230215_老人憩の家従事者数（常勤）",
                "@level": "1",
                "@unit": "人"
              },
              {
                "@code": "J230221",
                "@name": "J230221_有料老人ホーム数（詳細票）",
                "@level": "1",
                "@unit": "所"
              },
              {
                "@code": "J230222",
                "@name": "J230222_有料老人ホーム定員数（詳細票）",
                "@level": "1",
                "@unit": "人"
              },
              {
                "@code": "J230223",
                "@name": "J230223_有料老人ホーム在所者数（詳細票）",
                "@level": "1",
                "@unit": "人"
              },
              {
                "@code": "J230225",
                "@name": "J230225_有料老人ホーム従事者数（詳細票）（常勤）",
                "@level": "1",
                "@unit": "人"
              },
              {
                "@code": "J2303",
                "@name": "J2303_その他の社会福祉施設等数",
                "@level": "1",
                "@unit": "所"
              },
              {
                "@code": "J2304",
                "@name": "J2304_老人福祉施設数（基本票）",
                "@level": "1",
                "@unit": "所"
              },
              {
                "@code": "J230411",
                "@name": "J230411_養護老人ホーム数（基本票）",
                "@level": "1",
                "@unit": "所"
              },
              {
                "@code": "J230412",
                "@name": "J230412_養護老人ホーム定員数（基本票）",
                "@level": "1",
                "@unit": "人"
              },
              {
                "@code": "J230421",
                "@name": "J230421_有料老人ホーム数（基本票）",
                "@level": "1",
                "@unit": "所"
              },
              {
                "@code": "J230422",
                "@name": "J230422_有料老人ホーム定員数（基本票）",
                "@level": "1",
                "@unit": "人"
              },
              {
                "@code": "J230431",
                "@name": "J230431_軽費老人ホーム数（基本票）",
                "@level": "1",
                "@unit": "所"
              },
              {
                "@code": "J230432",
                "@name": "J230432_軽費老人ホーム定員数（基本票）",
                "@level": "1",
                "@unit": "人"
              },
              {
                "@code": "J232101",
                "@name": "J232101_老人ホーム数",
                "@level": "1",
                "@unit": "所"
              },
              {
                "@code": "J232102",
                "@name": "J232102_老人ホーム定員数",
                "@level": "1",
                "@unit": "人"
              },
              {
                "@code": "J232103",
                "@name": "J232103_老人ホーム在所者数",
                "@level": "1",
                "@unit": "人"
              },
              {
                "@code": "J232104",
                "@name": "J232104_老人ホーム従事者数（専任）",
                "@level": "1",
                "@unit": "人"
              },
              {
                "@code": "J232105",
                "@name": "J232105_老人ホーム従事者数（常勤）",
                "@level": "1",
                "@unit": "人"
              },
              {
                "@code": "J2401",
                "@name": "J2401_身体障害者更生援護施設数",
                "@level": "1",
                "@unit": "所"
              },
              {
                "@code": "J2402",
                "@name": "J2402_身体障害者更生援護施設定員数",
                "@level": "1",
                "@unit": "人"
              },
              {
                "@code": "J2403",
                "@name": "J2403_身体障害者更生援護施設在所者数",
                "@level": "1",
                "@unit": "人"
              },
              {
                "@code": "J2404",
                "@name": "J2404_身体障害者更生援護施設従事者数（専任）",
                "@level": "1",
                "@unit": "人"
              },
              {
                "@code": "J2405",
                "@name": "J2405_身体障害者更生援護施設従事者数（常勤）",
                "@level": "1",
                "@unit": "人"
              },
              {
                "@code": "J2501",
                "@name": "J2501_児童福祉施設等数（詳細票）",
                "@level": "1",
                "@unit": "所"
              },
              {
                "@code": "J250101",
                "@name": "J250101_児童福祉施設等数（詳細票）（保育所等を除く）",
                "@level": "1",
                "@unit": "所"
              },
              {
                "@code": "J250102",
                "@name": "J250102_児童福祉施設等数（基本票）（保育所等を除く）",
                "@level": "1",
                "@unit": "所"
              },
              {
                "@code": "J250201",
                "@name": "J250201_児童福祉施設従事者数（保育所、児童館、児童遊園を除く）（専任）",
                "@level": "1",
                "@unit": "人"
              },
              {
                "@code": "J250202",
                "@name": "J250202_児童福祉施設等従事者数（詳細票）（常勤）",
                "@level": "1",
                "@unit": "人"
              },
              {
                "@code": "J250203",
                "@name": "J250203_児童福祉施設等従事者数（詳細票）（保育所等を除く）（常勤）",
                "@level": "1",
                "@unit": "人"
              },
              {
                "@code": "J250204",
                "@name": "J250204_児童福祉施設等数（基本票）",
                "@level": "1",
                "@unit": "所"
              },
              {
                "@code": "J2503",
                "@name": "J2503_保育所等数（詳細票）",
                "@level": "1",
                "@unit": "所"
              },
              {
                "@code": "J250301",
                "@name": "J250301_公営保育所等数（詳細票）",
                "@level": "1",
                "@unit": "所"
              },
              {
                "@code": "J250302",
                "@name": "J250302_保育所等数（基本票）",
                "@level": "1",
                "@unit": "所"
              },
              {
                "@code": "J250303",
                "@name": "J250303_公営保育所等数（基本票）",
                "@level": "1",
                "@unit": "所"
              },
              {
                "@code": "J2504",
                "@name": "J2504_保育所保育士数（専任）",
                "@level": "1",
                "@unit": "人"
              },
              {
                "@code": "J2505",
                "@name": "J2505_保育所等定員数（詳細票）",
                "@level": "1",
                "@unit": "人"
              },
              {
                "@code": "J250501",
                "@name": "J250501_公営保育所等定員数（詳細票）",
                "@level": "1",
                "@unit": "人"
              },
              {
                "@code": "J250502",
                "@name": "J250502_保育所等利用待機児童数",
                "@level": "1",
                "@unit": "人"
              },
              {
                "@code": "J2506",
                "@name": "J2506_保育所等在所児数（詳細票）",
                "@level": "1",
                "@unit": "人"
              },
              {
                "@code": "J250601",
                "@name": "J250601_保育所在所児数（3歳児）",
                "@level": "1",
                "@unit": "人"
              },
              {
                "@code": "J250602",
                "@name": "J250602_保育所在所児数（4歳児）",
                "@level": "1",
                "@unit": "人"
              },
              {
                "@code": "J250603",
                "@name": "J250603_保育所在所児数（5歳児）",
                "@level": "1",
                "@unit": "人"
              },
              {
                "@code": "J250604",
                "@name": "J250604_公営保育所等在所児数（詳細票）",
                "@level": "1",
                "@unit": "人"
              },
              {
                "@code": "J2508",
                "@name": "J2508_保育所等修了者数（詳細票）",
                "@level": "1",
                "@unit": "人"
              },
              {
                "@code": "J2509",
                "@name": "J2509_児童館数",
                "@level": "1",
                "@unit": "所"
              },
              {
                "@code": "J2510",
                "@name": "J2510_児童遊園数",
                "@level": "1",
                "@unit": "所"
              },
              {
                "@code": "J2511",
                "@name": "J2511_助産施設数",
                "@level": "1",
                "@unit": "所"
              },
              {
                "@code": "J2513",
                "@name": "J2513_乳児院数",
                "@level": "1",
                "@unit": "所"
              },
              {
                "@code": "J2514",
                "@name": "J2514_乳児院定員数",
                "@level": "1",
                "@unit": "人"
              },
              {
                "@code": "J2515",
                "@name": "J2515_乳児院在所者数",
                "@level": "1",
                "@unit": "人"
              },
              {
                "@code": "J2517",
                "@name": "J2517_母子生活支援施設数",
                "@level": "1",
                "@unit": "所"
              },
              {
                "@code": "J2519",
                "@name": "J2519_母子生活支援施設在所者数",
                "@level": "1",
                "@unit": "人"
              },
              {
                "@code": "J2521",
                "@name": "J2521_児童養護施設数",
                "@level": "1",
                "@unit": "所"
              },
              {
                "@code": "J2522",
                "@name": "J2522_児童養護施設定員数",
                "@level": "1",
                "@unit": "人"
              },
              {
                "@code": "J2523",
                "@name": "J2523_児童養護施設在所者数",
                "@level": "1",
                "@unit": "人"
              },
              {
                "@code": "J2525",
                "@name": "J2525_心身障害児施設数",
                "@level": "1",
                "@unit": "所"
              },
              {
                "@code": "J252501",
                "@name": "J252501_知的障害児施設数",
                "@level": "1",
                "@unit": "所"
              },
              {
                "@code": "J252502",
                "@name": "J252502_知的障害児通園施設数",
                "@level": "1",
                "@unit": "所"
              },
              {
                "@code": "J252503",
                "@name": "J252503_盲児施設数",
                "@level": "1",
                "@unit": "所"
              },
              {
                "@code": "J252504",
                "@name": "J252504_ろうあ児施設数",
                "@level": "1",
                "@unit": "所"
              },
              {
                "@code": "J252505",
                "@name": "J252505_難聴幼児通園施設数",
                "@level": "1",
                "@unit": "所"
              },
              {
                "@code": "J252507",
                "@name": "J252507_肢体不自由児施設数",
                "@level": "1",
                "@unit": "所"
              },
              {
                "@code": "J252508",
                "@name": "J252508_肢体不自由児通園施設数",
                "@level": "1",
                "@unit": "所"
              },
              {
                "@code": "J252509",
                "@name": "J252509_肢体不自由児療護施設数",
                "@level": "1",
                "@unit": "所"
              },
              {
                "@code": "J252510",
                "@name": "J252510_重症心身障害児施設数",
                "@level": "1",
                "@unit": "所"
              },
              {
                "@code": "J252511",
                "@name": "J252511_情緒障害児短期治療施設数",
                "@level": "1",
                "@unit": "所"
              },
              {
                "@code": "J252512",
                "@name": "J252512_自閉症児施設数",
                "@level": "1",
                "@unit": "所"
              },
              {
                "@code": "J2526",
                "@name": "J2526_保育所等保育士数（詳細票）",
                "@level": "1",
                "@unit": "人"
              },
              {
                "@code": "J252601",
                "@name": "J252601_公営保育所等保育士数（詳細票）",
                "@level": "1",
                "@unit": "人"
              },
              {
                "@code": "J2527",
                "@name": "J2527_保育所従事者数（常勤）",
                "@level": "1",
                "@unit": "人"
              },
              {
                "@code": "J2528",
                "@name": "J2528_乳児院従事者数（常勤）",
                "@level": "1",
                "@unit": "人"
              },
              {
                "@code": "J2529",
                "@name": "J2529_母子生活支援施設従事者数（常勤）",
                "@level": "1",
                "@unit": "人"
              },
              {
                "@code": "J2530",
                "@name": "J2530_児童養護施設従事者数（常勤）",
                "@level": "1",
                "@unit": "人"
              },
              {
                "@code": "J2540",
                "@name": "J2540_認定こども園数",
                "@level": "1",
                "@unit": "園"
              },
              {
                "@code": "J2541",
                "@name": "J2541_認定こども園数（幼保連携型）",
                "@level": "1",
                "@unit": "園"
              },
              {
                "@code": "J2542",
                "@name": "J2542_認定こども園数（幼稚園型）",
                "@level": "1",
                "@unit": "園"
              },
              {
                "@code": "J2543",
                "@name": "J2543_認定こども園数（保育所型）",
                "@level": "1",
                "@unit": "園"
              },
              {
                "@code": "J2544",
                "@name": "J2544_認定こども園数（地方裁量型）",
                "@level": "1",
                "@unit": "園"
              },
              {
                "@code": "J2545",
                "@name": "J2545_幼保連携型認定こども園在所児数",
                "@level": "1",
                "@unit": "人"
              },
              {
                "@code": "J2546",
                "@name": "J2546_保育所型認定こども園在所児数",
                "@level": "1",
                "@unit": "人"
              },
              {
                "@code": "J2547",
                "@name": "J2547_小規模保育事業所数",
                "@level": "1",
                "@unit": "所"
              },
              {
                "@code": "J2548",
                "@name": "J2548_小規模保育事業所在所児数",
                "@level": "1",
                "@unit": "人"
              },
              {
                "@code": "J2626",
                "@name": "J2626_心身障害児施設定員数",
                "@level": "1",
                "@unit": "人"
              },
              {
                "@code": "J262601",
                "@name": "J262601_知的障害児施設定員数",
                "@level": "1",
                "@unit": "人"
              },
              {
                "@code": "J262602",
                "@name": "J262602_知的障害児通園施設定員数",
                "@level": "1",
                "@unit": "人"
              },
              {
                "@code": "J262608",
                "@name": "J262608_肢体不自由児通園施設定員数",
                "@level": "1",
                "@unit": "人"
              },
              {
                "@code": "J262610",
                "@name": "J262610_重症心身障害児施設定員数",
                "@level": "1",
                "@unit": "人"
              },
              {
                "@code": "J2627",
                "@name": "J2627_心身障害児施設在所者数",
                "@level": "1",
                "@unit": "人"
              },
              {
                "@code": "J262701",
                "@name": "J262701_知的障害児施設在所者数",
                "@level": "1",
                "@unit": "人"
              },
              {
                "@code": "J262703",
                "@name": "J262703_盲児施設在所者数",
                "@level": "1",
                "@unit": "人"
              },
              {
                "@code": "J262709",
                "@name": "J262709_肢体不自由児療護施設在所者数",
                "@level": "1",
                "@unit": "人"
              },
              {
                "@code": "J2629",
                "@name": "J2629_児童自立支援施設数",
                "@level": "1",
                "@unit": "所"
              },
              {
                "@code": "J2631",
                "@name": "J2631_児童自立支援施設在所者数",
                "@level": "1",
                "@unit": "人"
              },
              {
                "@code": "J2633",
                "@name": "J2633_児童自立支援施設従事者数（常勤）",
                "@level": "1",
                "@unit": "人"
              },
              {
                "@code": "J2634",
                "@name": "J2634_心身障害児施設従事者数（常勤）",
                "@level": "1",
                "@unit": "人"
              },
              {
                "@code": "J2641",
                "@name": "J2641_へき地保育所数",
                "@level": "1",
                "@unit": "所"
              },
              {
                "@code": "J2642",
                "@name": "J2642_へき地保育所在所児数",
                "@level": "1",
                "@unit": "人"
              },
              {
                "@code": "J2651",
                "@name": "J2651_認可外保育施設数",
                "@level": "1",
                "@unit": "施設"
              },
              {
                "@code": "J2652",
                "@name": "J2652_認可外保育施設利用児童数",
                "@level": "1",
                "@unit": "人"
              },
              {
                "@code": "J2701",
                "@name": "J2701_知的障害者援護施設数",
                "@level": "1",
                "@unit": "所"
              },
              {
                "@code": "J2702",
                "@name": "J2702_知的障害者援護施設定員数",
                "@level": "1",
                "@unit": "人"
              },
              {
                "@code": "J2703",
                "@name": "J2703_知的障害者援護施設在所者数",
                "@level": "1",
                "@unit": "人"
              },
              {
                "@code": "J2704",
                "@name": "J2704_知的障害者援護施設従事者数（専任）",
                "@level": "1",
                "@unit": "人"
              },
              {
                "@code": "J2705",
                "@name": "J2705_知的障害者援護施設従事者数（常勤）",
                "@level": "1",
                "@unit": "人"
              },
              {
                "@code": "J2801",
                "@name": "J2801_母子・父子福祉施設数（詳細票）",
                "@level": "1",
                "@unit": "所"
              },
              {
                "@code": "J2803",
                "@name": "J2803_母子・父子福祉施設従事者数（詳細票）（常勤）",
                "@level": "1",
                "@unit": "人"
              },
              {
                "@code": "J2804",
                "@name": "J2804_母子・父子福祉施設数（基本票）",
                "@level": "1",
                "@unit": "所"
              },
              {
                "@code": "J2901",
                "@name": "J2901_障害者支援施設等数（詳細票）",
                "@level": "1",
                "@unit": "所"
              },
              {
                "@code": "J2902",
                "@name": "J2902_精神障害者社会復帰施設数",
                "@level": "1",
                "@unit": "所"
              },
              {
                "@code": "J2903",
                "@name": "J2903_身体障害者社会参加支援施設数",
                "@level": "1",
                "@unit": "所"
              },
              {
                "@code": "J2904",
                "@name": "J2904_婦人保護施設数（詳細票）",
                "@level": "1",
                "@unit": "所"
              },
              {
                "@code": "J2905",
                "@name": "J2905_障害者支援施設等数（基本票）",
                "@level": "1",
                "@unit": "所"
              },
              {
                "@code": "J2906",
                "@name": "J2906_婦人保護施設数（基本票）",
                "@level": "1",
                "@unit": "所"
              },
              {
                "@code": "J3101",
                "@name": "J3101_民生委員（児童委員）数",
                "@level": "1",
                "@unit": "人"
              },
              {
                "@code": "J3108",
                "@name": "J3108_訪問介護員（ホームヘルパー）数",
                "@level": "1",
                "@unit": "人"
              },
              {
                "@code": "J3201",
                "@name": "J3201_民生委員（児童委員）相談・支援件数",
                "@level": "1",
                "@unit": "件"
              },
              {
                "@code": "J3202",
                "@name": "J3202_福祉事務所生活保護申請件数",
                "@level": "1",
                "@unit": "件"
              },
              {
                "@code": "J3203",
                "@name": "J3203_身体障害者更生援護取扱実人員",
                "@level": "1",
                "@unit": "人"
              },
              {
                "@code": "J3204",
                "@name": "J3204_福祉事務所知的障害者相談実人員",
                "@level": "1",
                "@unit": "人"
              },
              {
                "@code": "J3205",
                "@name": "J3205_身体障害者更生相談所取扱実人員",
                "@level": "1",
                "@unit": "人"
              },
              {
                "@code": "J3206",
                "@name": "J3206_知的障害者更生相談所取扱実人員",
                "@level": "1",
                "@unit": "人"
              },
              {
                "@code": "J3207",
                "@name": "J3207_児童相談所受付件数",
                "@level": "1",
                "@unit": "件"
              },
              {
                "@code": "J3208",
                "@name": "J3208_市町村における知的障害者相談実人員",
                "@level": "1",
                "@unit": "人"
              },
              {
                "@code": "J3209",
                "@name": "J3209_児童相談所における児童虐待相談の対応件数",
                "@level": "1",
                "@unit": "件"
              },
              {
                "@code": "J320901",
                "@name": "J320901_児童相談所における児童虐待相談の対応件数（被虐待者が0～2歳）",
                "@level": "1",
                "@unit": "件"
              },
              {
                "@code": "J320902",
                "@name": "J320902_児童相談所における児童虐待相談の対応件数（被虐待者が3～6歳）",
                "@level": "1",
                "@unit": "件"
              },
              {
                "@code": "J320903",
                "@name": "J320903_児童相談所における児童虐待相談の対応件数（被虐待者が7～12歳）",
                "@level": "1",
                "@unit": "件"
              },
              {
                "@code": "J320904",
                "@name": "J320904_児童相談所における児童虐待相談の対応件数（被虐待者が13～15歳）",
                "@level": "1",
                "@unit": "件"
              },
              {
                "@code": "J320905",
                "@name": "J320905_児童相談所における児童虐待相談の対応件数（被虐待者が16～18歳）",
                "@level": "1",
                "@unit": "件"
              },
              {
                "@code": "J4001",
                "@name": "J4001_国民医療費（総額）",
                "@level": "1",
                "@unit": "億円"
              },
              {
                "@code": "J4002",
                "@name": "J4002_国民医療費（一般診療）（入院）",
                "@level": "1",
                "@unit": "億円"
              },
              {
                "@code": "J4003",
                "@name": "J4003_国民医療費（一般診療）（入院外）",
                "@level": "1",
                "@unit": "億円"
              },
              {
                "@code": "J4004",
                "@name": "J4004_一人当たりの医療費",
                "@level": "1",
                "@unit": "千円"
              },
              {
                "@code": "J4005",
                "@name": "J4005_国民医療費（医科診療）（入院）",
                "@level": "1",
                "@unit": "億円"
              },
              {
                "@code": "J4006",
                "@name": "J4006_国民医療費（医科診療）（入院外）",
                "@level": "1",
                "@unit": "億円"
              },
              {
                "@code": "J4101",
                "@name": "J4101_国民健康保険被保険者数",
                "@level": "1",
                "@unit": "人"
              },
              {
                "@code": "J4102",
                "@name": "J4102_国民健康保険給付件数",
                "@level": "1",
                "@unit": "件"
              },
              {
                "@code": "J4104",
                "@name": "J4104_国民健康保険医療費件数（診療費）",
                "@level": "1",
                "@unit": "件"
              },
              {
                "@code": "J4105",
                "@name": "J4105_国民健康保険給付金額（診療費）（費用額）",
                "@level": "1",
                "@unit": "千円"
              },
              {
                "@code": "J4106",
                "@name": "J4106_国民健康保険被保険者受診率（1000人当たり）",
                "@level": "1",
                "@unit": "‐"
              },
              {
                "@code": "J4107",
                "@name": "J4107_国民健康保険被保険者1人当たり診療費",
                "@level": "1",
                "@unit": "円"
              },
              {
                "@code": "J4108",
                "@name": "J4108_国民健康保険給付金額",
                "@level": "1",
                "@unit": "千円"
              },
              {
                "@code": "J4109",
                "@name": "J4109_国民健康保険医療費金額（診療費）",
                "@level": "1",
                "@unit": "千円"
              },
              {
                "@code": "J4201",
                "@name": "J4201_全国健康保険協会管掌健康保険事業所数",
                "@level": "1",
                "@unit": "所"
              },
              {
                "@code": "J4202",
                "@name": "J4202_全国健康保険協会管掌健康保険被保険者数",
                "@level": "1",
                "@unit": "人"
              },
              {
                "@code": "J4203",
                "@name": "J4203_全国健康保険協会管掌健康保険被扶養者数",
                "@level": "1",
                "@unit": "人"
              },
              {
                "@code": "J4204",
                "@name": "J4204_全国健康保険協会管掌健康保険給付件数",
                "@level": "1",
                "@unit": "件"
              },
              {
                "@code": "J420401",
                "@name": "J420401_政府管掌健康保険給付件数（被保険者）",
                "@level": "1",
                "@unit": "件"
              },
              {
                "@code": "J420402",
                "@name": "J420402_政府管掌健康保険給付件数（被扶養者）",
                "@level": "1",
                "@unit": "件"
              },
              {
                "@code": "J420410",
                "@name": "J420410_全国健康保険協会管掌健康保険給付件数（診療費）",
                "@level": "1",
                "@unit": "件"
              },
              {
                "@code": "J420411",
                "@name": "J420411_全国健康保険協会管掌健康保険給付件数（診療費・被保険者）",
                "@level": "1",
                "@unit": "件"
              },
              {
                "@code": "J420412",
                "@name": "J420412_全国健康保険協会管掌健康保険給付件数（診療費・被扶養者）",
                "@level": "1",
                "@unit": "件"
              },
              {
                "@code": "J420421",
                "@name": "J420421_全国健康保険協会管掌健康保険受診率（被保険者）",
                "@level": "1",
                "@unit": "‐"
              },
              {
                "@code": "J420422",
                "@name": "J420422_全国健康保険協会管掌健康保険受診率（被扶養者）",
                "@level": "1",
                "@unit": "‐"
              },
              {
                "@code": "J4205",
                "@name": "J4205_全国健康保険協会管掌健康保険給付金額",
                "@level": "1",
                "@unit": "千円"
              },
              {
                "@code": "J420501",
                "@name": "J420501_政府管掌健康保険給付金額（被保険者）",
                "@level": "1",
                "@unit": "千円"
              },
              {
                "@code": "J420502",
                "@name": "J420502_政府管掌健康保険給付金額（被扶養者）",
                "@level": "1",
                "@unit": "千円"
              },
              {
                "@code": "J420510",
                "@name": "J420510_全国健康保険協会管掌健康保険給付金額（診療費）",
                "@level": "1",
                "@unit": "千円"
              },
              {
                "@code": "J420511",
                "@name": "J420511_全国健康保険協会管掌健康保険給付金額（診療費・被保険者）",
                "@level": "1",
                "@unit": "千円"
              },
              {
                "@code": "J420512",
                "@name": "J420512_全国健康保険協会管掌健康保険給付金額（診療費・被扶養者）",
                "@level": "1",
                "@unit": "千円"
              },
              {
                "@code": "J420521",
                "@name": "J420521_政府管掌健康保険1人当たり受診金額（被保険者）",
                "@level": "1",
                "@unit": "円"
              },
              {
                "@code": "J420522",
                "@name": "J420522_政府管掌健康保険1人当たり受診金額（被扶養者）",
                "@level": "1",
                "@unit": "円"
              },
              {
                "@code": "J420531",
                "@name": "J420531_全国健康保険協会管掌健康保険1人当たり医療費（被保険者）",
                "@level": "1",
                "@unit": "円"
              },
              {
                "@code": "J420532",
                "@name": "J420532_全国健康保険協会管掌健康保険1人当たり医療費（被扶養者）",
                "@level": "1",
                "@unit": "円"
              },
              {
                "@code": "J420533",
                "@name": "J420533_全国健康保険協会管掌健康保険1人当たり医療費（加入者合計）",
                "@level": "1",
                "@unit": "円"
              },
              {
                "@code": "J4206",
                "@name": "J4206_全国健康保険協会管掌健康保険1人当たり医療費の地域差指数",
                "@level": "1",
                "@unit": "－"
              },
              {
                "@code": "J4301",
                "@name": "J4301_組合管掌健康保険組合数",
                "@level": "1",
                "@unit": "組合"
              },
              {
                "@code": "J4302",
                "@name": "J4302_組合管掌健康保険被保険者数",
                "@level": "1",
                "@unit": "人"
              },
              {
                "@code": "J4303",
                "@name": "J4303_組合管掌健康保険被扶養者数",
                "@level": "1",
                "@unit": "人"
              },
              {
                "@code": "J4304",
                "@name": "J4304_組合管掌健康保険給付件数",
                "@level": "1",
                "@unit": "件"
              },
              {
                "@code": "J430401",
                "@name": "J430401_組合管掌健康保険給付件数（被保険者）",
                "@level": "1",
                "@unit": "件"
              },
              {
                "@code": "J430402",
                "@name": "J430402_組合管掌健康保険給付件数（被扶養者）",
                "@level": "1",
                "@unit": "件"
              },
              {
                "@code": "J430410",
                "@name": "J430410_組合管掌健康保険給付件数（診療費）",
                "@level": "1",
                "@unit": "件"
              },
              {
                "@code": "J430411",
                "@name": "J430411_組合管掌健康保険給付件数（診療費・被保険者）",
                "@level": "1",
                "@unit": "件"
              },
              {
                "@code": "J430412",
                "@name": "J430412_組合管掌健康保険給付件数（診療費・被扶養者）",
                "@level": "1",
                "@unit": "件"
              },
              {
                "@code": "J430421",
                "@name": "J430421_組合管掌健康保険受診率（被保険者）",
                "@level": "1",
                "@unit": "‐"
              },
              {
                "@code": "J430422",
                "@name": "J430422_組合管掌健康保険受診率（被扶養者）",
                "@level": "1",
                "@unit": "‐"
              },
              {
                "@code": "J4305",
                "@name": "J4305_組合管掌健康保険給付金額",
                "@level": "1",
                "@unit": "千円"
              },
              {
                "@code": "J430501",
                "@name": "J430501_組合管掌健康保険給付金額（被保険者）",
                "@level": "1",
                "@unit": "千円"
              },
              {
                "@code": "J430502",
                "@name": "J430502_組合管掌健康保険給付金額（被扶養者）",
                "@level": "1",
                "@unit": "千円"
              },
              {
                "@code": "J430510",
                "@name": "J430510_組合管掌健康保険給付金額（診療費）",
                "@level": "1",
                "@unit": "千円"
              },
              {
                "@code": "J430511",
                "@name": "J430511_組合管掌健康保険給付金額（診療費・被保険者）",
                "@level": "1",
                "@unit": "千円"
              },
              {
                "@code": "J430512",
                "@name": "J430512_組合管掌健康保険給付金額（診療費・被扶養者）",
                "@level": "1",
                "@unit": "千円"
              },
              {
                "@code": "J430521",
                "@name": "J430521_組合管掌健康保険1人当たり受診金額（被保険者）",
                "@level": "1",
                "@unit": "円"
              },
              {
                "@code": "J4401",
                "@name": "J4401_船員保険（疾病分）船舶所有者数",
                "@level": "1",
                "@unit": "人"
              },
              {
                "@code": "J4402",
                "@name": "J4402_船員保険（疾病分）被保険者数",
                "@level": "1",
                "@unit": "人"
              },
              {
                "@code": "J4403",
                "@name": "J4403_船員保険（疾病分）被扶養者数",
                "@level": "1",
                "@unit": "人"
              },
              {
                "@code": "J4404",
                "@name": "J4404_船員保険（疾病分）給付件数",
                "@level": "1",
                "@unit": "件"
              },
              {
                "@code": "J440401",
                "@name": "J440401_船員保険（疾病分）給付件数（被保険者）",
                "@level": "1",
                "@unit": "件"
              },
              {
                "@code": "J440402",
                "@name": "J440402_船員保険（疾病分）給付件数（被扶養者）",
                "@level": "1",
                "@unit": "件"
              },
              {
                "@code": "J440410",
                "@name": "J440410_船員保険（疾病分）給付件数（診療費）",
                "@level": "1",
                "@unit": "件"
              },
              {
                "@code": "J440411",
                "@name": "J440411_船員保険（疾病分）給付件数（診療費・被保険者）",
                "@level": "1",
                "@unit": "件"
              },
              {
                "@code": "J440412",
                "@name": "J440412_船員保険（疾病分）給付件数（診療費・被扶養者）",
                "@level": "1",
                "@unit": "件"
              },
              {
                "@code": "J4405",
                "@name": "J4405_船員保険（疾病分）給付金額",
                "@level": "1",
                "@unit": "千円"
              },
              {
                "@code": "J440501",
                "@name": "J440501_船員保険（疾病分）給付金額（被保険者）",
                "@level": "1",
                "@unit": "千円"
              },
              {
                "@code": "J440502",
                "@name": "J440502_船員保険（疾病分）給付金額（被扶養者）",
                "@level": "1",
                "@unit": "千円"
              },
              {
                "@code": "J440510",
                "@name": "J440510_船員保険（疾病分）給付金額（診療費）",
                "@level": "1",
                "@unit": "千円"
              },
              {
                "@code": "J440511",
                "@name": "J440511_船員保険（疾病分）給付金額（診療費・被保険者）",
                "@level": "1",
                "@unit": "千円"
              },
              {
                "@code": "J440512",
                "@name": "J440512_船員保険（疾病分）給付金額（診療費・被扶養者）",
                "@level": "1",
                "@unit": "千円"
              },
              {
                "@code": "J4501",
                "@name": "J4501_後期高齢者医療被保険者数",
                "@level": "1",
                "@unit": "人"
              },
              {
                "@code": "J4502",
                "@name": "J4502_老人医療受給件数",
                "@level": "1",
                "@unit": "件"
              },
              {
                "@code": "J450210",
                "@name": "J450210_老人医療受給件数（診療費）",
                "@level": "1",
                "@unit": "件"
              },
              {
                "@code": "J450220",
                "@name": "J450220_老人医療受診率（1000人当たり）",
                "@level": "1",
                "@unit": "‐"
              },
              {
                "@code": "J4503",
                "@name": "J4503_後期高齢者医療費",
                "@level": "1",
                "@unit": "千円"
              },
              {
                "@code": "J450310",
                "@name": "J450310_老人医療費（診療費）",
                "@level": "1",
                "@unit": "千円"
              },
              {
                "@code": "J450320",
                "@name": "J450320_1人当たり後期高齢者医療費",
                "@level": "1",
                "@unit": "円"
              },
              {
                "@code": "J5101",
                "@name": "J5101_厚生年金保険適用事業所数",
                "@level": "1",
                "@unit": "所"
              },
              {
                "@code": "J5102",
                "@name": "J5102_厚生年金保険被保険者数",
                "@level": "1",
                "@unit": "人"
              },
              {
                "@code": "J5103",
                "@name": "J5103_厚生年金保険受給権者数",
                "@level": "1",
                "@unit": "人"
              },
              {
                "@code": "J510301",
                "@name": "J510301_厚生年金保険受給権者数（老齢年金）",
                "@level": "1",
                "@unit": "人"
              },
              {
                "@code": "J510302",
                "@name": "J510302_厚生年金保険受給権者数（通算老齢年金）",
                "@level": "1",
                "@unit": "人"
              },
              {
                "@code": "J510303",
                "@name": "J510303_厚生年金保険受給権者数（障害年金）",
                "@level": "1",
                "@unit": "人"
              },
              {
                "@code": "J510304",
                "@name": "J510304_厚生年金保険受給権者数（遺族年金）",
                "@level": "1",
                "@unit": "人"
              },
              {
                "@code": "J510305",
                "@name": "J510305_厚生年金保険受給権者数（通算遺族年金）",
                "@level": "1",
                "@unit": "人"
              },
              {
                "@code": "J5104",
                "@name": "J5104_厚生年金保険受給権者年金総額",
                "@level": "1",
                "@unit": "千円"
              },
              {
                "@code": "J510401",
                "@name": "J510401_厚生年金保険受給権者年金総額（老齢年金）",
                "@level": "1",
                "@unit": "千円"
              },
              {
                "@code": "J5201",
                "@name": "J5201_国民年金被保険者数",
                "@level": "1",
                "@unit": "人"
              },
              {
                "@code": "J520101",
                "@name": "J520101_国民年金第1号被保険者数",
                "@level": "1",
                "@unit": "人"
              },
              {
                "@code": "J520102",
                "@name": "J520102_国民年金第3号被保険者数",
                "@level": "1",
                "@unit": "人"
              },
              {
                "@code": "J520111",
                "@name": "J520111_国民年金保険料全額免除割合",
                "@level": "1",
                "@unit": "％"
              },
              {
                "@code": "J520112",
                "@name": "J520112_国民年金保険料申請一部免除割合",
                "@level": "1",
                "@unit": "％"
              },
              {
                "@code": "J520120",
                "@name": "J520120_国民年金保険料納付率",
                "@level": "1",
                "@unit": "％"
              },
              {
                "@code": "J5202",
                "@name": "J5202_国民年金受給権者数",
                "@level": "1",
                "@unit": "人"
              },
              {
                "@code": "J520201",
                "@name": "J520201_国民年金受給権者数（老齢年金）",
                "@level": "1",
                "@unit": "人"
              },
              {
                "@code": "J520202",
                "@name": "J520202_国民年金受給権者数（通算老齢年金）",
                "@level": "1",
                "@unit": "人"
              },
              {
                "@code": "J520203",
                "@name": "J520203_国民年金受給権者数（障害年金）",
                "@level": "1",
                "@unit": "人"
              },
              {
                "@code": "J520204",
                "@name": "J520204_国民年金受給権者数（遺族年金）",
                "@level": "1",
                "@unit": "人"
              },
              {
                "@code": "J5203",
                "@name": "J5203_国民年金受給権者年金総額",
                "@level": "1",
                "@unit": "千円"
              },
              {
                "@code": "J520301",
                "@name": "J520301_国民年金受給権者年金総額（老齢年金）",
                "@level": "1",
                "@unit": "千円"
              },
              {
                "@code": "J5301",
                "@name": "J5301_福祉年金受給者数",
                "@level": "1",
                "@unit": "人"
              },
              {
                "@code": "J5302",
                "@name": "J5302_福祉年金支給年額",
                "@level": "1",
                "@unit": "千円"
              },
              {
                "@code": "J6101",
                "@name": "J6101_雇用保険適用事業所数",
                "@level": "1",
                "@unit": "所"
              },
              {
                "@code": "J6102",
                "@name": "J6102_雇用保険被保険者数",
                "@level": "1",
                "@unit": "人"
              },
              {
                "@code": "J6103",
                "@name": "J6103_雇用保険求職者給付支給額",
                "@level": "1",
                "@unit": "円"
              },
              {
                "@code": "J6104",
                "@name": "J6104_雇用保険基本手当支給額",
                "@level": "1",
                "@unit": "円"
              },
              {
                "@code": "J6105",
                "@name": "J6105_雇用保険基本手当受給者実人員",
                "@level": "1",
                "@unit": "人"
              },
              {
                "@code": "J6106",
                "@name": "J6106_雇用保険基本手当受給資格決定件数",
                "@level": "1",
                "@unit": "件"
              },
              {
                "@code": "J6107",
                "@name": "J6107_雇用保険基本手当初回受給者数",
                "@level": "1",
                "@unit": "人"
              },
              {
                "@code": "J610701",
                "@name": "J610701_雇用保険基本手当初回受給者数（45歳以上）",
                "@level": "1",
                "@unit": "人"
              },
              {
                "@code": "J6109",
                "@name": "J6109_雇用保険（日雇）労働被保険者数",
                "@level": "1",
                "@unit": "人"
              },
              {
                "@code": "J6110",
                "@name": "J6110_雇用保険（日雇）受給者実人員",
                "@level": "1",
                "@unit": "人"
              },
              {
                "@code": "J6111",
                "@name": "J6111_雇用保険（日雇）給付支給額",
                "@level": "1",
                "@unit": "千円"
              },
              {
                "@code": "J6201",
                "@name": "J6201_船員保険（失業分）船舶所有者数",
                "@level": "1",
                "@unit": "人"
              },
              {
                "@code": "J6202",
                "@name": "J6202_船員保険（失業分）被保険者数",
                "@level": "1",
                "@unit": "人"
              },
              {
                "@code": "J6203",
                "@name": "J6203_船員保険（失業分）失業保険金給付件数",
                "@level": "1",
                "@unit": "件"
              },
              {
                "@code": "J6204",
                "@name": "J6204_船員保険（失業分）失業保険金給付金額",
                "@level": "1",
                "@unit": "千円"
              },
              {
                "@code": "J6301",
                "@name": "J6301_労働者災害補償保険適用事業場数",
                "@level": "1",
                "@unit": "事業場"
              },
              {
                "@code": "J6302",
                "@name": "J6302_労働者災害補償保険適用労働者数",
                "@level": "1",
                "@unit": "人"
              },
              {
                "@code": "J6303",
                "@name": "J6303_労働者災害補償保険給付件数",
                "@level": "1",
                "@unit": "件"
              },
              {
                "@code": "J6304",
                "@name": "J6304_労働者災害補償保険給付支給額",
                "@level": "1",
                "@unit": "円"
              },
              {
                "@code": "J7101",
                "@name": "J7101_介護保険給付（件数）",
                "@level": "1",
                "@unit": "件"
              },
              {
                "@code": "J710101",
                "@name": "J710101_居宅介護（支援）サービス介護給付（件数）",
                "@level": "1",
                "@unit": "件"
              },
              {
                "@code": "J710102",
                "@name": "J710102_施設介護サービス介護給付（件数）",
                "@level": "1",
                "@unit": "件"
              },
              {
                "@code": "J7102",
                "@name": "J7102_介護保険給付（費用額）",
                "@level": "1",
                "@unit": "千円"
              },
              {
                "@code": "J710201",
                "@name": "J710201_居宅介護（支援）サービス介護給付（費用額）",
                "@level": "1",
                "@unit": "千円"
              },
              {
                "@code": "J710202",
                "@name": "J710202_施設介護サービス介護給付（費用額）",
                "@level": "1",
                "@unit": "千円"
              },
              {
                "@code": "J7103",
                "@name": "J7103_介護保険給付（支給額）",
                "@level": "1",
                "@unit": "千円"
              },
              {
                "@code": "J710301",
                "@name": "J710301_居宅介護（支援）サービス介護給付（支給額）",
                "@level": "1",
                "@unit": "千円"
              },
              {
                "@code": "J710302",
                "@name": "J710302_施設介護サービス介護給付（支給額）",
                "@level": "1",
                "@unit": "千円"
              }
            ]
          },
          {
            "@id": "area",
            "@name": "地域",
            "CLASS": [
              {
                "@code": "00000",
                "@name": "全国",
                "@level": "1"
              },
              {
                "@code": "01000",
                "@name": "北海道",
                "@level": "2"
              },
              {
                "@code": "02000",
                "@name": "青森県",
                "@level": "2"
              },
              {
                "@code": "03000",
                "@name": "岩手県",
                "@level": "2"
              },
              {
                "@code": "04000",
                "@name": "宮城県",
                "@level": "2"
              },
              {
                "@code": "05000",
                "@name": "秋田県",
                "@level": "2"
              },
              {
                "@code": "06000",
                "@name": "山形県",
                "@level": "2"
              },
              {
                "@code": "07000",
                "@name": "福島県",
                "@level": "2"
              },
              {
                "@code": "08000",
                "@name": "茨城県",
                "@level": "2"
              },
              {
                "@code": "09000",
                "@name": "栃木県",
                "@level": "2"
              },
              {
                "@code": "10000",
                "@name": "群馬県",
                "@level": "2"
              },
              {
                "@code": "11000",
                "@name": "埼玉県",
                "@level": "2"
              },
              {
                "@code": "12000",
                "@name": "千葉県",
                "@level": "2"
              },
              {
                "@code": "13000",
                "@name": "東京都",
                "@level": "2"
              },
              {
                "@code": "14000",
                "@name": "神奈川県",
                "@level": "2"
              },
              {
                "@code": "15000",
                "@name": "新潟県",
                "@level": "2"
              },
              {
                "@code": "16000",
                "@name": "富山県",
                "@level": "2"
              },
              {
                "@code": "17000",
                "@name": "石川県",
                "@level": "2"
              },
              {
                "@code": "18000",
                "@name": "福井県",
                "@level": "2"
              },
              {
                "@code": "19000",
                "@name": "山梨県",
                "@level": "2"
              },
              {
                "@code": "20000",
                "@name": "長野県",
                "@level": "2"
              },
              {
                "@code": "21000",
                "@name": "岐阜県",
                "@level": "2"
              },
              {
                "@code": "22000",
                "@name": "静岡県",
                "@level": "2"
              },
              {
                "@code": "23000",
                "@name": "愛知県",
                "@level": "2"
              },
              {
                "@code": "24000",
                "@name": "三重県",
                "@level": "2"
              },
              {
                "@code": "25000",
                "@name": "滋賀県",
                "@level": "2"
              },
              {
                "@code": "26000",
                "@name": "京都府",
                "@level": "2"
              },
              {
                "@code": "27000",
                "@name": "大阪府",
                "@level": "2"
              },
              {
                "@code": "28000",
                "@name": "兵庫県",
                "@level": "2"
              },
              {
                "@code": "29000",
                "@name": "奈良県",
                "@level": "2"
              },
              {
                "@code": "30000",
                "@name": "和歌山県",
                "@level": "2"
              },
              {
                "@code": "31000",
                "@name": "鳥取県",
                "@level": "2"
              },
              {
                "@code": "32000",
                "@name": "島根県",
                "@level": "2"
              },
              {
                "@code": "33000",
                "@name": "岡山県",
                "@level": "2"
              },
              {
                "@code": "34000",
                "@name": "広島県",
                "@level": "2"
              },
              {
                "@code": "35000",
                "@name": "山口県",
                "@level": "2"
              },
              {
                "@code": "36000",
                "@name": "徳島県",
                "@level": "2"
              },
              {
                "@code": "37000",
                "@name": "香川県",
                "@level": "2"
              },
              {
                "@code": "38000",
                "@name": "愛媛県",
                "@level": "2"
              },
              {
                "@code": "39000",
                "@name": "高知県",
                "@level": "2"
              },
              {
                "@code": "40000",
                "@name": "福岡県",
                "@level": "2"
              },
              {
                "@code": "41000",
                "@name": "佐賀県",
                "@level": "2"
              },
              {
                "@code": "42000",
                "@name": "長崎県",
                "@level": "2"
              },
              {
                "@code": "43000",
                "@name": "熊本県",
                "@level": "2"
              },
              {
                "@code": "44000",
                "@name": "大分県",
                "@level": "2"
              },
              {
                "@code": "45000",
                "@name": "宮崎県",
                "@level": "2"
              },
              {
                "@code": "46000",
                "@name": "鹿児島県",
                "@level": "2"
              },
              {
                "@code": "47000",
                "@name": "沖縄県",
                "@level": "2"
              }
            ]
          },
          {
            "@id": "time",
            "@name": "調査年",
            "CLASS": [
              {
                "@code": "1975100000",
                "@name": "1975年度",
                "@level": "1"
              },
              {
                "@code": "1976100000",
                "@name": "1976年度",
                "@level": "1"
              },
              {
                "@code": "1977100000",
                "@name": "1977年度",
                "@level": "1"
              },
              {
                "@code": "1978100000",
                "@name": "1978年度",
                "@level": "1"
              },
              {
                "@code": "1979100000",
                "@name": "1979年度",
                "@level": "1"
              },
              {
                "@code": "1980100000",
                "@name": "1980年度",
                "@level": "1"
              },
              {
                "@code": "1981100000",
                "@name": "1981年度",
                "@level": "1"
              },
              {
                "@code": "1982100000",
                "@name": "1982年度",
                "@level": "1"
              },
              {
                "@code": "1983100000",
                "@name": "1983年度",
                "@level": "1"
              },
              {
                "@code": "1984100000",
                "@name": "1984年度",
                "@level": "1"
              },
              {
                "@code": "1985100000",
                "@name": "1985年度",
                "@level": "1"
              },
              {
                "@code": "1986100000",
                "@name": "1986年度",
                "@level": "1"
              },
              {
                "@code": "1987100000",
                "@name": "1987年度",
                "@level": "1"
              },
              {
                "@code": "1988100000",
                "@name": "1988年度",
                "@level": "1"
              },
              {
                "@code": "1989100000",
                "@name": "1989年度",
                "@level": "1"
              },
              {
                "@code": "1990100000",
                "@name": "1990年度",
                "@level": "1"
              },
              {
                "@code": "1991100000",
                "@name": "1991年度",
                "@level": "1"
              },
              {
                "@code": "1992100000",
                "@name": "1992年度",
                "@level": "1"
              },
              {
                "@code": "1993100000",
                "@name": "1993年度",
                "@level": "1"
              },
              {
                "@code": "1994100000",
                "@name": "1994年度",
                "@level": "1"
              },
              {
                "@code": "1995100000",
                "@name": "1995年度",
                "@level": "1"
              },
              {
                "@code": "1996100000",
                "@name": "1996年度",
                "@level": "1"
              },
              {
                "@code": "1997100000",
                "@name": "1997年度",
                "@level": "1"
              },
              {
                "@code": "1998100000",
                "@name": "1998年度",
                "@level": "1"
              },
              {
                "@code": "1999100000",
                "@name": "1999年度",
                "@level": "1"
              },
              {
                "@code": "2000100000",
                "@name": "2000年度",
                "@level": "1"
              },
              {
                "@code": "2001100000",
                "@name": "2001年度",
                "@level": "1"
              },
              {
                "@code": "2002100000",
                "@name": "2002年度",
                "@level": "1"
              },
              {
                "@code": "2003100000",
                "@name": "2003年度",
                "@level": "1"
              },
              {
                "@code": "2004100000",
                "@name": "2004年度",
                "@level": "1"
              },
              {
                "@code": "2005100000",
                "@name": "2005年度",
                "@level": "1"
              },
              {
                "@code": "2006100000",
                "@name": "2006年度",
                "@level": "1"
              },
              {
                "@code": "2007100000",
                "@name": "2007年度",
                "@level": "1"
              },
              {
                "@code": "2008100000",
                "@name": "2008年度",
                "@level": "1"
              },
              {
                "@code": "2009100000",
                "@name": "2009年度",
                "@level": "1"
              },
              {
                "@code": "2010100000",
                "@name": "2010年度",
                "@level": "1"
              },
              {
                "@code": "2011100000",
                "@name": "2011年度",
                "@level": "1"
              },
              {
                "@code": "2012100000",
                "@name": "2012年度",
                "@level": "1"
              },
              {
                "@code": "2013100000",
                "@name": "2013年度",
                "@level": "1"
              },
              {
                "@code": "2014100000",
                "@name": "2014年度",
                "@level": "1"
              },
              {
                "@code": "2015100000",
                "@name": "2015年度",
                "@level": "1"
              },
              {
                "@code": "2016100000",
                "@name": "2016年度",
                "@level": "1"
              },
              {
                "@code": "2017100000",
                "@name": "2017年度",
                "@level": "1"
              },
              {
                "@code": "2018100000",
                "@name": "2018年度",
                "@level": "1"
              },
              {
                "@code": "2019100000",
                "@name": "2019年度",
                "@level": "1"
              },
              {
                "@code": "2020100000",
                "@name": "2020年度",
                "@level": "1"
              },
              {
                "@code": "2021100000",
                "@name": "2021年度",
                "@level": "1"
              },
              {
                "@code": "2022100000",
                "@name": "2022年度",
                "@level": "1"
              },
              {
                "@code": "2023100000",
                "@name": "2023年度",
                "@level": "1"
              }
            ]
          }
        ]
      }
    }
  }
}