{
  "main": {
    "id": "4f114ac3606b4295",
    "type": "split",
    "children": [
      {
        "id": "16cd2fade29c2453",
        "type": "tabs",
        "children": [
          {
            "id": "eb0280c82c106835",
            "type": "leaf",
            "state": {
              "type": "markdown",
              "state": {
                "file": "01_development_guide/deployment_guide.md",
                "mode": "source",
                "source": false
              },
              "icon": "lucide-file",
              "title": "deployment_guide"
            }
          },
          {
            "id": "f98fab6543d4c123",
            "type": "leaf",
            "state": {
              "type": "markdown",
              "state": {
                "file": "01_development_guide/data-fetching-strategy.md",
                "mode": "source",
                "source": false
              },
              "icon": "lucide-file",
              "title": "data-fetching-strategy"
            }
          },
          {
            "id": "4faa4294089ffb3e",
            "type": "leaf",
            "state": {
              "type": "markdown",
              "state": {
                "file": "01_development_guide/component_guide.md",
                "mode": "source",
                "source": false
              },
              "icon": "lucide-file",
              "title": "component_guide"
            }
          },
          {
            "id": "1b2c24de311d3577",
            "type": "leaf",
            "state": {
              "type": "markdown",
              "state": {
                "file": "01_development_guide/documentation_management.md",
                "mode": "source",
                "source": false
              },
              "icon": "lucide-file",
              "title": "documentation_management"
            }
          }
        ],
        "currentTab": 3
      }
    ],
    "direction": "vertical"
  },
  "left": {
    "id": "50ff58c470a4a136",
    "type": "split",
    "children": [
      {
        "id": "5ee186e6106be43c",
        "type": "tabs",
        "children": [
          {
            "id": "860eb1f2bf495c69",
            "type": "leaf",
            "state": {
              "type": "file-explorer",
              "state": {
                "sortOrder": "alphabetical",
                "autoReveal": false
              },
              "icon": "lucide-folder-closed",
              "title": "ファイルエクスプローラ"
            }
          },
          {
            "id": "a8b6a35ecc29e5b5",
            "type": "leaf",
            "state": {
              "type": "search",
              "state": {
                "query": "",
                "matchingCase": false,
                "explainSearch": false,
                "collapseAll": false,
                "extraContext": false,
                "sortOrder": "alphabetical"
              },
              "icon": "lucide-search",
              "title": "検索"
            }
          },
          {
            "id": "ebea38cb8b94ad48",
            "type": "leaf",
            "state": {
              "type": "bookmarks",
              "state": {},
              "icon": "lucide-bookmark",
              "title": "ブックマーク"
            }
          }
        ]
      }
    ],
    "direction": "horizontal",
    "width": 232.5
  },
  "right": {
    "id": "8ed870fdff91f44c",
    "type": "split",
    "children": [
      {
        "id": "b90d79240d48f3e9",
        "type": "tabs",
        "children": [
          {
            "id": "df70d06db1e43817",
            "type": "leaf",
            "state": {
              "type": "backlink",
              "state": {
                "file": "02_domain/dashboard/implementation/best-practices.md",
                "collapseAll": false,
                "extraContext": false,
                "sortOrder": "alphabetical",
                "showSearch": false,
                "searchQuery": "",
                "backlinkCollapsed": false,
                "unlinkedCollapsed": true
              },
              "icon": "links-coming-in",
              "title": "best-practicesへのバックリンク"
            }
          },
          {
            "id": "6dce3cb1f191fe33",
            "type": "leaf",
            "state": {
              "type": "outgoing-link",
              "state": {
                "linksCollapsed": false,
                "unlinkedCollapsed": true
              },
              "icon": "links-going-out",
              "title": "アウトゴーイングリンク"
            }
          },
          {
            "id": "ec34d3a6ce1aacbf",
            "type": "leaf",
            "state": {
              "type": "tag",
              "state": {
                "sortOrder": "frequency",
                "useHierarchy": true,
                "showSearch": false,
                "searchQuery": ""
              },
              "icon": "lucide-tags",
              "title": "タグ"
            }
          },
          {
            "id": "d873db75767a7e2f",
            "type": "leaf",
            "state": {
              "type": "outline",
              "state": {
                "file": "01_development_guide/documentation_management.md",
                "followCursor": false,
                "showSearch": false,
                "searchQuery": ""
              },
              "icon": "lucide-list",
              "title": "documentation_managementのアウトライン"
            }
          }
        ],
        "currentTab": 3
      }
    ],
    "direction": "horizontal",
    "width": 300
  },
  "left-ribbon": {
    "hiddenItems": {
      "switcher:クイックスイッチャーを開く": false,
      "graph:グラフビューを開く": false,
      "canvas:新規キャンバスを作成": false,
      "daily-notes:今日のデイリーノートを開く": false,
      "templates:テンプレートを挿入": false,
      "command-palette:コマンドパレットを開く": false,
      "bases:Create new base": false,
      "float-search:Search obsidian in modal view": false
    }
  },
  "active": "1b2c24de311d3577",
  "lastOpenFiles": [
    "02_domain/database/operations/troubleshooting.md",
    "02_domain/database/operations/backup-restore.md",
    "02_domain/database/implementation/best-practices.md",
    "02_domain/database/implementation/query-patterns.md",
    "02_domain/database/specifications/migration-guide.md",
    "02_domain/database/specifications/schema-reference.md",
    "02_domain/database/implementation/development-setup.md",
    "02_domain/database/operations",
    "02_domain/database/implementation",
    "02_domain/database/specifications/database-design.md",
    "02_domain/blog/features/comments-guide.md",
    "01_development_guide/engagement_features.md",
    "02_domain/blog/features/engagement-features-guide.md",
    "02_domain/blog/features",
    "01_development_guide/documentation_management.md",
    "01_development_guide/component_guide.md",
    "01_development_guide/data-fetching-strategy.md",
    "01_development_guide/deployment_guide.md",
    "01_development_guide/nextjs-optimization-guide.md",
    "02_domain/ranking/implementation/ranking-configuration-guide.md",
    "01_development_guide/coding_standards.md",
    "01_development_guide/performance_optimization.md",
    "01_development_guide/environment_variables.md",
    "01_development_guide/large_scale_implementation.md",
    "00_project_overview/reference_links.md",
    "01_development_guide/d3js_choropleth_guide.md",
    "02_domain/visualization/implementation/d3js/d3js_choropleth_guide.md",
    "00_project_overview/world-statistics-integration-plan.md",
    "00_project_overview/world-statistics-api-integration-plan.md",
    "02_domain/export/implementation",
    "02_domain/export/specifications",
    "02_domain/export",
    "00_project_overview/japan-statistics-api-integration-plan.md.tmp.30336.1760650634494",
    "00_project_overview/japan-statistics-api-integration-plan.md.tmp.30336.1760650626442",
    "02_domain/visualization/patterns",
    "02_domain/architecture",
    "05_resources/都道府県ごとの物価分析.png",
    "05_resources/就職率.png",
    "05_resources/都道府県別産業割合.png",
    "05_resources/ランキング画像サンプル_02.png",
    "05_resources/転入転出.png",
    "05_resources/design.png",
    "05_resources/ランキング画像サンプル_01.png",
    "05_資料/design.png",
    "05_資料/都道府県別産業割合.png",
    "05_資料/都道府県ごとの物価分析.png"
  ]
}